setup.py
my_practice_probability/Binomialdistribution.py
my_practice_probability/Gaussiandistribution.py
my_practice_probability/Generaldistribution.py
my_practice_probability/__init__.py
my_practice_probability.egg-info/PKG-INFO
my_practice_probability.egg-info/SOURCES.txt
my_practice_probability.egg-info/dependency_links.txt
my_practice_probability.egg-info/not-zip-safe
my_practice_probability.egg-info/top_level.txt