Metadata-Version: 1.0
Name: my-practice-probability
Version: 1.2
Summary: Gaussian and Binomial distributions
Home-page: UNKNOWN
Author: Andrew Paster
Author-email: myemail@something.com
License: UNKNOWN
Platform: UNKNOWN
